<?xml version="1.0" encoding="UTF-8"?>
<LanguageData>
  
  <!-- EN: free and approved -->
  <Lovin_FreeApproved.label>libre et approuvé</Lovin_FreeApproved.label>
  <!-- EN: The physical act of love is a noble thing, no matter who does it with whom. -->
  <Lovin_FreeApproved.description>L'acte physique d'amour est une chose noble, peu importe qui le fait avec qui.</Lovin_FreeApproved.description>
  
  <!-- EN: horrible -->
  <Lovin_Horrible.label>horrible</Lovin_Horrible.label>
  <!-- EN: The physical act of lust is vile, though within marriage it is necessary. -->
  <Lovin_Horrible.description>L'acte physique du désir est ignoble, bien que dans le mariage il soit nécessaire.</Lovin_Horrible.description>
  <!-- EN: Lustful act with non-spouse -->
  <Lovin_Horrible.comps.1.description>Acte lubrique avec amant</Lovin_Horrible.comps.1.description>
  <!-- EN: Lustful act with spouse -->
  <Lovin_Horrible.comps.3.description>Acte lubrique avec conjoint</Lovin_Horrible.comps.3.description>
  
  <!-- EN: prohibited -->
  <Lovin_Prohibited.label>interdit</Lovin_Prohibited.label>
  <!-- EN: The physical act of lust is always vile, disgusting, and wrong. -->
  <Lovin_Prohibited.description>L'acte physique du désir est toujours vil et dégoûtant.</Lovin_Prohibited.description>
  <!-- EN: Lustful act -->
  <Lovin_Prohibited.comps.1.description>Acte lubrique avec amant</Lovin_Prohibited.comps.1.description>
  
  <!-- EN: spouse only (mild) -->
  <Lovin_SpouseOnly_Mild.label>conjoint seulement (léger)</Lovin_SpouseOnly_Mild.label>
  <!-- EN: Though it's understandable to make love with another outside of marriage, it's not a good thing. -->
  <Lovin_SpouseOnly_Mild.description>Bien qu'il soit compréhensible de faire l'amour avec quelqu'un d'autre en dehors du mariage, ce n'est pas une bonne chose.</Lovin_SpouseOnly_Mild.description>
  <!-- EN: Lustful act with non-spouse -->
  <Lovin_SpouseOnly_Mild.comps.1.description>Acte lubrique avec amant</Lovin_SpouseOnly_Mild.comps.1.description>
  
  <!-- EN: spouse only (moderate) -->
  <Lovin_SpouseOnly_Moderate.label>conjoint seulement (modéré)</Lovin_SpouseOnly_Moderate.label>
  <!-- EN: To make love with another outside of marriage is wrong. -->
  <Lovin_SpouseOnly_Moderate.description>Faire l'amour avec quelqu'un en dehors du mariage est mal.</Lovin_SpouseOnly_Moderate.description>
  <!-- EN: Lustful act with non-spouse -->
  <Lovin_SpouseOnly_Moderate.comps.1.description>Acte lubrique avec amant</Lovin_SpouseOnly_Moderate.comps.1.description>
  
  <!-- EN: spouse only (strict) -->
  <Lovin_SpouseOnly_Strict.label>conjoint seulement (strict)</Lovin_SpouseOnly_Strict.label>
  <!-- EN: To make love with another outside of marriage is deeply immoral. -->
  <Lovin_SpouseOnly_Strict.description>Faire l'amour avec quelqu'un en dehors du mariage est profondément immoral.</Lovin_SpouseOnly_Strict.description>
  <!-- EN: Lustful act with non-spouse -->
  <Lovin_SpouseOnly_Strict.comps.1.description>Acte lubrique avec amant</Lovin_SpouseOnly_Strict.comps.1.description>
  
</LanguageData>