<?xml version="1.0" encoding="UTF-8"?>
<LanguageData>
  
  <!-- EN:
    <li>questDescription->[enemiesLabel] have set up a camp and are harassing caravans of [asker_faction_name]. [asker_nameDef] is planning an aerial assault on the camp, which is guarded by [enemiesCount] [enemiesLabel]. [asker_pronoun] wants you to provide [soldiers] to carry out the attack.\n\n[asker_pronoun] will send a shuttle to pick up your fighters, bring them to the attack site, and take them home afterward. They will be fed and medically tended en-route.\n\nOnce the attack begins, you must defeat all enemies and turrets within [timeoutTicks_duration].</li>
    <li>soldiers(requiredPawnCount>1)->[requiredPawnCount] soldiers</li>
    <li>soldiers(requiredPawnCount==1)->[requiredPawnCount] soldier</li>
  -->
  <Mission_BanditCamp.questDescriptionRules.rulesStrings>
    <li>questDescription->Des [enemiesLabel] ont installé un camp et harcèlent les caravanes de [asker_faction_name]. [asker_nameDef] planifie un assaut aérien sur le camp, qui est gardé par [enemiesCount] [enemiesLabel]. [asker_pronoun] souhaite que vous fournissiez [soldiers] pour mener l'attaque.\n\n[asker_pronoun] enverra une navette pour récupérer vos combattants, les amener sur le site de l'attaque et les ramener chez vous par la suite. Ils seront nourris et soignés en route.\n\nUne fois l'attaque commencée, vous devrez vaincre tous les ennemis et tourelles dans un délai de [timeoutTicks_duration].</li>
    <li>soldiers(requiredPawnCount>1)->[requiredPawnCount] soldats</li>
    <li>soldiers(requiredPawnCount==1)->[requiredPawnCount] soldat</li>
  </Mission_BanditCamp.questDescriptionRules.rulesStrings>
  <!-- EN:
    <li>questName->[questNameInner]</li>
    <li>questName->[asker_nameDef]'s [questNameInner]</li>
    <li>questNameInner->[aerial] [attack]</li>
    <li>questNameInner->[target] [attack]</li>
    <li>questNameInner->[attack] [work]</li>
    <li>target->camp</li>
    <li>target->base</li>
    <li>target->fort</li>
    <li>aerial->aerial</li>
    <li>aerial->air</li>
    <li>aerial->shuttle-borne</li>
    <li>attack->attack</li>
    <li>attack->assault</li>
    <li>work->work</li>
    <li>work->job</li>
  -->
  <Mission_BanditCamp.questNameRules.rulesStrings>
    <li>questName->[questNameInner]</li>
    <li>questName->[questNameInner] de [asker_nameDef]</li>
    <li>questNameInner->[attack] [aerial]</li>
    <li>questNameInner->[attack] [target]</li>
    <li>questNameInner->[attack] [work]</li>
    <li>target->sur le camp</li>
    <li>target->sur la base</li>
    <li>target->sur le bastion</li>
    <li>aerial->aérienne</li>
    <li>aerial->par les airs</li>
    <li>aerial->aéroportée</li>
    <li>attack->attaque</li>
    <li>attack->agression</li>
    <li>work->pour une récompense</li>
    <li>work->pour un contrat</li>
  </Mission_BanditCamp.questNameRules.rulesStrings>
  
</LanguageData>