<?xml version="1.0" encoding="UTF-8"?>
<LanguageData>
  
  <!-- EN: blood rain -->
  <BloodRain.label>pluie sanglante</BloodRain.label>
  <!-- EN: Blood rain -->
  <BloodRain.letterLabel>Pluie sanglante</BloodRain.letterLabel>
  
  <!-- EN: creepjoiner join -->
  <CreepJoinerJoin.label>un creepjoiner rejoint</CreepJoinerJoin.label>
  
  <!-- EN: creepjoiner join -->
  <CreepJoinerJoin_Metalhorror.label>un creepjoiner rejoint</CreepJoinerJoin_Metalhorror.label>
  
  <!-- EN: death pall -->
  <DeathPall.label>brume funeste</DeathPall.label>
  <!-- EN: Death pall -->
  <DeathPall.letterLabel>Brume funeste</DeathPall.letterLabel>
  
  <!-- EN: fleshmass heart -->
  <FleshmassHeart.label>cœur de masse de chair</FleshmassHeart.label>
  <!-- EN: Something from below -->
  <FleshmassHeart.letterLabel>Mystère des profondeurs</FleshmassHeart.letterLabel>
  <!-- EN: A small circle of terrain has begun to shift and crack apart. Something is digging up towards the surface. Rhythmic pulsations shake the ground from underneath. -->
  <FleshmassHeart.letterText>Un petit bout de terrain a commencé à glisser et à se fissurer. D'après les pulsations qui parviennent du sous-sol, quelque chose cherche à rejoindre la surface.</FleshmassHeart.letterText>
  
  <!-- EN: distress signal -->
  <GiveQuest_DistressCall.label>signal de détresse</GiveQuest_DistressCall.label>
  <!-- EN: Distress signal -->
  <GiveQuest_DistressCall.letterLabel>Signal de détresse</GiveQuest_DistressCall.letterLabel>
  
  <!-- EN: golden cube arrival -->
  <GoldenCubeArrival.label>arrivée du cube doré</GoldenCubeArrival.label>
  
  <!-- EN: harbinger tree -->
  <HarbingerTreeProvoked.label>arbre-héraut</HarbingerTreeProvoked.label>
  <!-- EN: Harbinger tree sprout -->
  <HarbingerTreeProvoked.letterLabel>Pousse d’arbre annonciateur</HarbingerTreeProvoked.letterLabel>
  <!-- EN: A harbinger tree has sprouted nearby. These gnarled trees grow flesh-like coverings, and can feed on corpses and raw meat placed nearby. If well fed, the grove will continue to grow.\n\nIn a tribal myth, these trees are the emissaries of a shapeless god who rules an endless black ocean. The myth ends after the shapeless god reaches up from the water and tears down the sky. -->
  <HarbingerTreeProvoked.letterText>Un arbre-héraut a poussé à proximité. Ces arbres noueux développent une écorce semblable à de la chair et peuvent se nourrir de cadavres et de viande crue déposés à côté. S'ils sont bien nourris, le bosquet continuera à croître.\n\nSelon un mythe tribal, ces arbres sont les émissaires d’un dieu informe régnant sur un océan noir infini. Le mythe se termine lorsque ce dieu informe surgit de l’eau et déchire le ciel.</HarbingerTreeProvoked.letterText>
  
  <!-- EN: metalhorror implantation -->
  <MetalhorrorImplantation.label>implantation d'horreur métallique</MetalhorrorImplantation.label>
  
  <!-- EN: mysterious cargo cube -->
  <MysteriousCargoCube.label>mystérieuse marchandise : cube</MysteriousCargoCube.label>
  
  <!-- EN: mysterious cargo revenant spine -->
  <MysteriousCargoRevenantSpine.label>mystérieuse marchandise : colonne de revenant</MysteriousCargoRevenantSpine.label>
  
  <!-- EN: mysterious cargo corpse -->
  <MysteriousCargoUnnaturalCorpse.label>mystérieuse marchandise : cadavre</MysteriousCargoUnnaturalCorpse.label>
  
  <!-- EN: nociosphere -->
  <Nociosphere.label>nociosphère</Nociosphere.label>
  <!-- EN: Nociosphere -->
  <Nociosphere.letterLabel>Nociosphère</Nociosphere.letterLabel>
  <!-- EN: A strange metallic sphere has appeared. It hurts to be near it.\n\nYou could attack it, though you're not sure how it might defend itself. Or, you could capture it using a holding platform and learn to make use of its power.\n\nIt seems quiet for now, but it is gaining energy over time. You can suppress the sphere when it is captured to a holding platform, reducing its energy. -->
  <Nociosphere.letterText>Une étrange sphère métallique est apparue. Quiconque s'en approche ressent une certaine souffrance.\n\nVous pourriez l'attaquer, mais prendriez le risque qu'elle se défende. Vous pouvez aussi la capturer à l'aide d'une plateforme de détention afin d'apprendre à exploiter son pouvoir.\n\nElle est pour l'instant inoffensive, mais accumule de l'énergie au fil du temps. Si vous la capturez à l'aide d'une plateforme de détention, vous pouvez réprimer la sphère et ainsi réduire son énergie.</Nociosphere.letterText>
  
  <!-- EN: pit gate -->
  <PitGate.label>fosse</PitGate.label>
  <!-- EN: Pit gate opening -->
  <PitGate.letterLabel>Apparition d'une fosse</PitGate.letterLabel>
  <!-- EN: A wide piece of terrain has begun sinking into the depths, forming a deepening hole. At this rate, it will deepen out of sight within a day. You can hear inhuman shrieks rising from the depths.\n\nMove buildings and items away from the emergence point. -->
  <PitGate.letterText>Une grande portion de terrain a commencé à s'enfoncer dans les profondeurs, formant un trou de plus en plus profond dont s'élèvent des cris inhumains. À ce rythme, vous n'en verrez plus le fond d'ici une journée.\n\nÉloignez les bâtiments et les objets du point d'émergence.</PitGate.letterText>
  
  <!-- EN: revenant emergence -->
  <RevenantEmergence.label>émergence de revenant</RevenantEmergence.label>
  <!-- EN: Revenant spine humming -->
  <RevenantEmergence.letterLabel>Bourdonnement de colonne de revenant</RevenantEmergence.letterLabel>
  <!-- EN: The revenant spine is becoming more active and emitting an ominous hum. Destroy it or restrain it on a holding platform before it's too late. -->
  <RevenantEmergence.letterText>La colonne de revenant est de plus en plus active et produit une sorte de bourdonnement sinistre. Détruisez-la ou confinez-la sur une plateforme de détention avant qu'il ne soit trop tard.</RevenantEmergence.letterText>
  
  <!-- EN: unnatural corpse arrival -->
  <UnnaturalCorpseArrival.label>arrivée de cadavre anormal</UnnaturalCorpseArrival.label>
  
  <!-- EN: unnatural darkness -->
  <UnnaturalDarkness.label>obscurité surnaturelle</UnnaturalDarkness.label>
  
  <!-- EN: warped obelisk -->
  <WarpedObelisk_Abductor.label>obélisque dénaturé</WarpedObelisk_Abductor.label>
  <!-- EN: Warped obelisk -->
  <WarpedObelisk_Abductor.letterLabel>Obélisque dénaturé</WarpedObelisk_Abductor.letterLabel>
  <!-- EN: A mysterious obelisk has crashed nearby.\n\nThe obelisk hums with putrid psychic energy, gradually intensifying as it approaches some dangerous limit. You can send colonists to suppress the obelisk to prevent it from activating.\n\nYou can also mark the obelisk for study to try to learn its purpose and perhaps make use of it.\n\nYou can always attack the obelisk to destroy it, but doing so may unleash unnatural and dangerous phenomena. -->
  <WarpedObelisk_Abductor.letterText>Un mystérieux obélisque s'est écrasé à proximité.\n\nL'obélisque bourdonne d'une énergie psychique putride de plus en plus intense qui risque d'atteindre des seuils dangereux. Vous pouvez envoyer des colons pour empêcher l'obélisque de s'activer.\n\nIl est également possible de l'étudier afin d'essayer de déterminer à quoi il sert et s'il peut vous être utile.\n\nVous pouvez aussi attaquer l'obélisque pour le détruire, mais risquez de provoquer des réactions surnaturelles et pour le moins dangereuses.</WarpedObelisk_Abductor.letterText>
  
  <!-- EN: corrupted obelisk -->
  <WarpedObelisk_Duplicator.label>obélisque corrompu</WarpedObelisk_Duplicator.label>
  <!-- EN: Corrupted obelisk -->
  <WarpedObelisk_Duplicator.letterLabel>Obélisque corrompu</WarpedObelisk_Duplicator.letterLabel>
  <!-- EN: A mysterious obelisk has crashed nearby.\n\nThe obelisk hums with putrid psychic energy, gradually intensifying as it approaches some dangerous limit. You can send colonists to suppress the obelisk to prevent it from activating.\n\nYou can also mark the obelisk for study to try to learn its purpose and perhaps make use of it.\n\nYou can always attack the obelisk to destroy it, but doing so may unleash unnatural and dangerous phenomena. -->
  <WarpedObelisk_Duplicator.letterText>Un mystérieux obélisque s'est écrasé à proximité.\n\nL'obélisque bourdonne d'une énergie psychique putride de plus en plus intense qui risque d'atteindre des seuils dangereux. Vous pouvez envoyer des colons pour empêcher l'obélisque de s'activer.\n\nIl est également possible de l'étudier afin d'essayer de déterminer à quoi il sert et s'il peut vous être utile.\n\nVous pouvez aussi attaquer l'obélisque pour le détruire, mais risquez de provoquer des réactions surnaturelles et pour le moins dangereuses.</WarpedObelisk_Duplicator.letterText>
  
  <!-- EN: twisted obelisk -->
  <WarpedObelisk_Mutator.label>obélisque difforme</WarpedObelisk_Mutator.label>
  <!-- EN: Twisted obelisk -->
  <WarpedObelisk_Mutator.letterLabel>Obélisque difforme</WarpedObelisk_Mutator.letterLabel>
  <!-- EN: A mysterious obelisk has crashed nearby.\n\nThe obelisk hums with putrid psychic energy, gradually intensifying as it approaches some dangerous limit. You can send colonists to suppress the obelisk to prevent it from activating.\n\nYou can also mark the obelisk for study to try to learn its purpose and perhaps make use of it.\n\nYou can always attack the obelisk to destroy it, but doing so may unleash unnatural and dangerous phenomena. -->
  <WarpedObelisk_Mutator.letterText>Un mystérieux obélisque s'est écrasé à proximité.\n\nL'obélisque bourdonne d'une énergie psychique putride de plus en plus intense qui risque d'atteindre des seuils dangereux. Vous pouvez envoyer des colons pour empêcher l'obélisque de s'activer.\n\nIl est également possible de l'étudier afin d'essayer de déterminer à quoi il sert et s'il peut vous être utile.\n\nVous pouvez aussi attaquer l'obélisque pour le détruire, mais risquez de provoquer des réactions surnaturelles et pour le moins dangereuses.</WarpedObelisk_Mutator.letterText>
  
</LanguageData>