<?xml version="1.0" encoding="UTF-8"?>
<LanguageData>
  
  <!-- EN: ate without table -->
  <AteWithoutTable.stages.ate_without_table.label>a mangé sans table</AteWithoutTable.stages.ate_without_table.label>
  <!-- EN: I had to eat a meal off the ground. Can't we get a table around here? -->
  <AteWithoutTable.stages.ate_without_table.description>J'ai dû manger sans table. Quelqu'un peut-il fabriquer une fichue table ?</AteWithoutTable.stages.ate_without_table.description>
  
  <!-- EN: bonded animal {0} banished -->
  <BondedAnimalBanished.stages.bonded_animal_banished.label>animal lié {0} banni</BondedAnimalBanished.stages.bonded_animal_banished.label>
  <!-- EN: My bonded animal was banished! -->
  <BondedAnimalBanished.stages.bonded_animal_banished.description>Mon animal favori a été banni !</BondedAnimalBanished.stages.bonded_animal_banished.description>
  
  <!-- EN: I butchered humanlike -->
  <ButcheredHumanlikeCorpse.stages.I_butchered_humanlike.label>a dépecé un humanoïde</ButcheredHumanlikeCorpse.stages.I_butchered_humanlike.label>
  <!-- EN: I butchered someone up like an animal. -->
  <ButcheredHumanlikeCorpse.stages.I_butchered_humanlike.description>J'ai dépecé quelqu'un comme un vulgaire animal.</ButcheredHumanlikeCorpse.stages.I_butchered_humanlike.description>
  
  <!-- EN: catharsis -->
  <Catharsis.stages.catharsis.label>catharsis</Catharsis.stages.catharsis.label>
  <!-- EN: It felt good to finally unbottle my feelings. -->
  <Catharsis.stages.catharsis.description>Ce qui vient d'arriver… ça ne me ressemble pas. Je sais que je peux faire mieux que ça.</Catharsis.stages.catharsis.description>
  
  <!-- EN: colonist banished -->
  <ColonistBanished.stages.colonist_banished.label>colon banni</ColonistBanished.stages.colonist_banished.label>
  <!-- EN: We just banished someone. I hope they'll make it, but I'm worried. -->
  <ColonistBanished.stages.colonist_banished.description>Nous avons banni quelqu'un. J'espère qu'il s'en sortira, mais je suis inqui{PAWN_gender ? et : ète}.</ColonistBanished.stages.colonist_banished.description>
  
  <!-- EN: colonist banished to death -->
  <ColonistBanishedToDie.stages.colonist_banished_to_death.label>colon banni et abandonné à sa mort</ColonistBanishedToDie.stages.colonist_banished_to_death.label>
  <!-- EN: We banished someone in such a way that there's almost no way they'll survive. -->
  <ColonistBanishedToDie.stages.colonist_banished_to_death.description>Nous avons banni quelqu'un. Il n'y a presque aucun moyen qu'il survive.</ColonistBanishedToDie.stages.colonist_banished_to_death.description>
  
  <!-- EN: defeated hostile leader {0} -->
  <DefeatedHostileFactionLeader.stages.defeated_hostile_leader.label>a vaincu le chef ennemi {0}</DefeatedHostileFactionLeader.stages.defeated_hostile_leader.label>
  <!-- EN: They were leading efforts to destroy us, and I took them down! -->
  <DefeatedHostileFactionLeader.stages.defeated_hostile_leader.description>Ils s'efforçaient de nous détruire, mais j'ai abattu leur meneur !</DefeatedHostileFactionLeader.stages.defeated_hostile_leader.description>
  
  <!-- EN: defeated hostile leader -->
  <DefeatedHostileFactionLeaderOpinion.stages.defeated_hostile_leader.label>a vaincu le chef ennemi</DefeatedHostileFactionLeaderOpinion.stages.defeated_hostile_leader.label>
  
  <!-- EN: defeated mech cluster -->
  <DefeatedMechCluster.stages.defeated_mech_cluster.label>a vaincu une ruche mécanoïde</DefeatedMechCluster.stages.defeated_mech_cluster.label>
  <!-- EN: Blood beats metal, you damn machines! -->
  <DefeatedMechCluster.stages.defeated_mech_cluster.description>La chair a vaincu le métal, sacrés machines !</DefeatedMechCluster.stages.defeated_mech_cluster.description>
  
  <!-- EN: failed to rescue {0} -->
  <FailedToRescueRelative.stages.failed_to_rescue.label>échec du sauvetage de {0}</FailedToRescueRelative.stages.failed_to_rescue.label>
  <!-- EN: We had a chance to rescue my relative, and failed. I could have helped! -->
  <FailedToRescueRelative.stages.failed_to_rescue.description>Nous n'avons pas réussi à sauver un de mes proches. Sachant que j'aurais pu l'aider, il m'est encore plus difficile de faire face à la mort d'un être cher.</FailedToRescueRelative.stages.failed_to_rescue.description>
  
  <!-- EN: freed from slavery -->
  <FreedFromSlavery.stages.freed_from_slavery.label>libéré{PAWN_gender ? : e} de l'esclavage</FreedFromSlavery.stages.freed_from_slavery.label>
  <!-- EN: I have been freed from slavery. I'm so thankful! -->
  <FreedFromSlavery.stages.freed_from_slavery.description>J'ai été libéré{PAWN_gender ? : e} de l'esclavage. Je suis tellement reconnaissant{PAWN_gender ? : e} !</FreedFromSlavery.stages.freed_from_slavery.description>
  
  <!-- EN: killed someone -->
  <KilledHumanlikeBloodlust.stages.killed_someone.label>a tué quelqu'un</KilledHumanlikeBloodlust.stages.killed_someone.label>
  <!-- EN: I killed someone! What a rush! -->
  <KilledHumanlikeBloodlust.stages.killed_someone.description>J'ai tué quelqu'un. Cette sensation, c'est si bon !</KilledHumanlikeBloodlust.stages.killed_someone.description>
  
  <!-- EN: buried in sarcophagus -->
  <KnowBuriedInSarcophagus.stages.buried_in_sarcophagus.label>enterrement dans un sarcophage</KnowBuriedInSarcophagus.stages.buried_in_sarcophagus.label>
  <!-- EN: This colony buried someone in an ornamented sarcophagus. May their soul rest in peace. -->
  <KnowBuriedInSarcophagus.stages.buried_in_sarcophagus.description>Cette colonie a enterré quelqu'un dans un sarcophage ornementé. Son âme doit pouvoir reposer en paix dorénavant.</KnowBuriedInSarcophagus.stages.buried_in_sarcophagus.description>
  
  <!-- EN: we butchered humanlike -->
  <KnowButcheredHumanlikeCorpse.stages.we_butchered_humanlike.label>Nous avons charcuté un humain</KnowButcheredHumanlikeCorpse.stages.we_butchered_humanlike.label>
  <!-- EN: We butchered someone up like an animal. -->
  <KnowButcheredHumanlikeCorpse.stages.we_butchered_humanlike.description>Nous avons charcuté un humain comme nous l'aurions fait avec un animal.</KnowButcheredHumanlikeCorpse.stages.we_butchered_humanlike.description>
  
  <!-- EN: colonist's organ harvested -->
  <KnowColonistOrganHarvested.stages.colonists_organ_harvested.label>organe prélevé d'un colon</KnowColonistOrganHarvested.stages.colonists_organ_harvested.label>
  <!-- EN: Someone took body parts from a colonist. It's horrible, breaking someone down for parts when they have no choice. -->
  <KnowColonistOrganHarvested.stages.colonists_organ_harvested.description>Quelqu'un a pris une partie du corps d'un colon. C'est horrible de faire ça à quelqu'un sans lui laisser le choix.</KnowColonistOrganHarvested.stages.colonists_organ_harvested.description>
  
  <!-- EN: someone's organ harvested -->
  <KnowGuestOrganHarvested.stages.someones_organ_harvested.label>un organe a été prélevé sur quelqu'un</KnowGuestOrganHarvested.stages.someones_organ_harvested.label>
  <!-- EN: The colony took body parts from a guest or prisoner. It's horrible, breaking someone down for parts when they have no choice. -->
  <KnowGuestOrganHarvested.stages.someones_organ_harvested.description>La colonie a pris les organes d'un prisonnier ou d'un invité. C'est horrible de faire ça à quelqu'un sans lui laisser le choix.</KnowGuestOrganHarvested.stages.someones_organ_harvested.description>
  
  <!-- EN: prisoner sold -->
  <KnowPrisonerSold.stages.prisoner_sold.label>prisonnier vendu</KnowPrisonerSold.stages.prisoner_sold.label>
  <!-- EN: This colony sold a prisoner into slavery. That's a worrying thought. -->
  <KnowPrisonerSold.stages.prisoner_sold.description>Cette colonie a vendu un prisonnier en esclavage. C'est une idée inquiétante.</KnowPrisonerSold.stages.prisoner_sold.description>
  
  <!-- EN: my organ harvested -->
  <MyOrganHarvested.stages.my_organ_harvested.label>organe prélevé</MyOrganHarvested.stages.my_organ_harvested.label>
  <!-- EN: The colony harvested body parts from me! They're breaking me down like an old engine! -->
  <MyOrganHarvested.stages.my_organ_harvested.description>La colonie m'a pris{PAWN_gender ? : e} un de mes organes ! Ils me réduisent en pièces détachées, comme si j'étais un vieux moteur !</MyOrganHarvested.stages.my_organ_harvested.description>
  
  <!-- EN: initial hope -->
  <NewColonyHope.stages.initial_hope.label>plein{PAWN_gender ? : e} d'espoir</NewColonyHope.stages.initial_hope.label>
  <!-- EN: I'm getting used to this, but it's still an exciting new situation. I hope this works out... -->
  <NewColonyHope.stages.initial_hope.description>Je commence à m'habituer, mais tout ça reste nouveau pour moi. J'espère que tout ira bien…</NewColonyHope.stages.initial_hope.description>
  
  <!-- EN: initial optimism -->
  <NewColonyOptimism.stages.initial_optimism.label>optimisme des premiers jours</NewColonyOptimism.stages.initial_optimism.label>
  <!-- EN: It's a tough situation, but I'm excited to be founding a new settlement. -->
  <NewColonyOptimism.stages.initial_optimism.description>Nous venons d'atterrir. Ce sera dur, mais je suis tout{PAWN_gender ? : e} excité{PAWN_gender ? : e} à l'idée de fonder une nouvelle colonie.</NewColonyOptimism.stages.initial_optimism.description>
  
  <!-- EN: nuzzled -->
  <Nuzzled.stages.nuzzled.label>caressé{PAWN_gender ? : e}</Nuzzled.stages.nuzzled.label>
  <!-- EN: A cute animal nuzzled me. -->
  <Nuzzled.stages.nuzzled.description>Un animal mignon s'est blotti contre moi.</Nuzzled.stages.nuzzled.description>
  
  <!-- EN: observed corpse -->
  <ObservedLayingCorpse.stages.observed_corpse.label>vient de voir un cadavre</ObservedLayingCorpse.stages.observed_corpse.label>
  <!-- EN: I saw a dead body laying on the ground. It was disturbing. -->
  <ObservedLayingCorpse.stages.observed_corpse.description>J'ai vu un cadavre là-bas.</ObservedLayingCorpse.stages.observed_corpse.description>
  
  <!-- EN: observed rotting corpse -->
  <ObservedLayingRottingCorpse.stages.observed_rotting_corpse.label>vient de voir un cadavre putréfié</ObservedLayingRottingCorpse.stages.observed_rotting_corpse.label>
  <!-- EN: I saw a rotting corpse laying on the ground. It was disgusting. -->
  <ObservedLayingRottingCorpse.stages.observed_rotting_corpse.description>J'ai vu un cadavre putréfié là-bas. C'est dégoûtant.</ObservedLayingRottingCorpse.stages.observed_rotting_corpse.description>
  
  <!-- EN: on duty -->
  <OnDuty.stages.on_duty.label>en service</OnDuty.stages.on_duty.label>
  <!-- EN: I have a job to do. -->
  <OnDuty.stages.on_duty.description>J'ai un travail à faire.</OnDuty.stages.on_duty.description>
  
  <!-- EN: prisoner banished to death -->
  <PrisonerBanishedToDie.stages.prisoner_banished_to_death.label>prisonnier banni et abandonné à sa mort</PrisonerBanishedToDie.stages.prisoner_banished_to_death.label>
  <!-- EN: We banished a prisoner in such a way that there's almost no way they'll survive. -->
  <PrisonerBanishedToDie.stages.prisoner_banished_to_death.description>Nous avons banni un prisonnier. Il n'y a presque aucun moyen qu'il survive.</PrisonerBanishedToDie.stages.prisoner_banished_to_death.description>
  
  <!-- EN: prisoner released -->
  <ReleasedHealthyPrisoner.stages.prisoner_released.label>prisonnier libéré</ReleasedHealthyPrisoner.stages.prisoner_released.label>
  <!-- EN: We released a healthy prisoner. It feels good to know we even treat prisoners well. -->
  <ReleasedHealthyPrisoner.stages.prisoner_released.description>Nous avons libéré un prisonnier en bonne santé. Cela fait plaisir de savoir que nous traitons bien autrui, même quand c'est un prisonnier.</ReleasedHealthyPrisoner.stages.prisoner_released.description>
  
  <!-- EN: rescued -->
  <Rescued.stages.rescued.label>sauvé{PAWN_gender ? : e}</Rescued.stages.rescued.label>
  <!-- EN: I was rescued! I almost thought I was done for back there. I'm so thankful. -->
  <Rescued.stages.rescued.description>J'ai été sauvé{PAWN_gender ? : e} ! J'ai presque pensé que j'allais finir comme ça. Je suis tellement reconnaissant{PAWN_gender ? : e}.</Rescued.stages.rescued.description>
  
  <!-- EN: rescued {0} -->
  <RescuedRelative.stages.rescued.label>sauvetage de {0} réussi</RescuedRelative.stages.rescued.label>
  <!-- EN: We rescued one of my relatives. Finally, I can breathe a sigh of relief. -->
  <RescuedRelative.stages.rescued.description>Nous avons sauvé un de mes proches. Maintenant je peux enfin pousser un soupir de soulagement.</RescuedRelative.stages.rescued.description>
  
  <!-- EN: disturbed sleep -->
  <SleepDisturbed.stages.disturbed_sleep.label>sommeil troublé</SleepDisturbed.stages.disturbed_sleep.label>
  <!-- EN: I was disturbed during sleep by people moving around nearby. A private room would solve this. -->
  <SleepDisturbed.stages.disturbed_sleep.description>Mon sommeil a été troublé par des personnes qui se déplaçaient à l'intérieur de la salle. Une chambre personnelle résoudrait cela.</SleepDisturbed.stages.disturbed_sleep.description>
  
  <!-- EN: slept in the cold -->
  <SleptInCold.stages.slept_in_the_cold.label>a dormi dans le froid</SleptInCold.stages.slept_in_the_cold.label>
  <!-- EN: I had to sleep in the cold. We really need some heaters. -->
  <SleptInCold.stages.slept_in_the_cold.description>J'ai dû dormir dans un endroit froid. Il nous faut vraiment un radiateur.</SleptInCold.stages.slept_in_the_cold.description>
  
  <!-- EN: slept in the heat -->
  <SleptInHeat.stages.slept_in_the_heat.label>a dormi dans la chaleur</SleptInHeat.stages.slept_in_the_heat.label>
  <!-- EN: I had to sleep in unbearable heat. Can't we have air conditioning? -->
  <SleptInHeat.stages.slept_in_the_heat.description>J'ai dormi dans une chaleur insupportable. De l'air conditionné, c'est trop demander ?</SleptInHeat.stages.slept_in_the_heat.description>
  
  <!-- EN: slept on ground -->
  <SleptOnGround.stages.slept_on_ground.label>a dormi par terre</SleptOnGround.stages.slept_on_ground.label>
  <!-- EN: I had to sleep on the ground like an animal. -->
  <SleptOnGround.stages.slept_on_ground.description>J'ai dû dormir par terre, comme un animal.</SleptOnGround.stages.slept_on_ground.description>
  
  <!-- EN: slept outside -->
  <SleptOutside.stages.slept_outside.label>a dormi dehors</SleptOutside.stages.slept_outside.label>
  <!-- EN: I had to sleep outdoors without any protection from the elements. -->
  <SleptOutside.stages.slept_outside.description>Il a fallu que je dorme dehors, sans aucune protection contre les éléments.</SleptOutside.stages.slept_outside.description>
  
  <!-- EN: soaking wet -->
  <SoakingWet.stages.soaking_wet.label>trempé{PAWN_gender ? : e} jusqu'aux os</SoakingWet.stages.soaking_wet.label>
  <!-- EN: I'm soaking wet. -->
  <SoakingWet.stages.soaking_wet.description>Je suis trempé{PAWN_gender ? : e} jusqu'aux os.</SoakingWet.stages.soaking_wet.description>
  
  <!-- EN: was imprisoned -->
  <WasImprisoned.stages.was_imprisoned.label>a été emprisonné{PAWN_gender ? : e}</WasImprisoned.stages.was_imprisoned.label>
  <!-- EN: The colony had me in jail for a while, like a caged animal. -->
  <WasImprisoned.stages.was_imprisoned.description>La colonie m'a gardé{PAWN_gender ? : e} en prison, comme un vulgaire animal en cage.</WasImprisoned.stages.was_imprisoned.description>
  
  <!-- EN: witnessed ally's death -->
  <WitnessedDeathAlly.stages.witnessed_allys_death.label>a vu mourir un allié</WitnessedDeathAlly.stages.witnessed_allys_death.label>
  <!-- EN: I saw one of my people die. They were alive one moment, and dead the next. -->
  <WitnessedDeathAlly.stages.witnessed_allys_death.description>J'ai vu mourir un proche. L'instant d'avant il était là… et maintenant, il est mort.</WitnessedDeathAlly.stages.witnessed_allys_death.description>
  
  <!-- EN: witnessed death with bloodlust -->
  <WitnessedDeathBloodlust.stages.witnessed_death_with_bloodlust.label>a vu la mort (soif de sang)</WitnessedDeathBloodlust.stages.witnessed_death_with_bloodlust.label>
  <!-- EN: I saw someone die! That was intense! -->
  <WitnessedDeathBloodlust.stages.witnessed_death_with_bloodlust.description>J'ai vu quelqu'un mourir ! C'était intense !</WitnessedDeathBloodlust.stages.witnessed_death_with_bloodlust.description>
  
  <!-- EN: witnessed family member's death -->
  <WitnessedDeathFamily.stages.witnessed_family_members_death.label>a vu mourir de la famille</WitnessedDeathFamily.stages.witnessed_family_members_death.label>
  <!-- EN: I saw a member of my family die. My own flesh and blood... -->
  <WitnessedDeathFamily.stages.witnessed_family_members_death.description>J'ai vu un membre de ma famille mourir. Ma chair, mon sang…</WitnessedDeathFamily.stages.witnessed_family_members_death.description>
  
  <!-- EN: witnessed outsider's death -->
  <WitnessedDeathNonAlly.stages.witnessed_outsiders_death.label>a vu mourir un inconnu</WitnessedDeathNonAlly.stages.witnessed_outsiders_death.label>
  <!-- EN: I saw someone die. They were alive one moment, and dead the next. -->
  <WitnessedDeathNonAlly.stages.witnessed_outsiders_death.description>J'ai vu mourir un étranger. L'instant d'avant il était là… et maintenant, il est mort.</WitnessedDeathNonAlly.stages.witnessed_outsiders_death.description>
  
</LanguageData>