<?xml version="1.0" encoding="UTF-8"?>
<LanguageData>
  
  <!-- EN: aiming time -->
  <AimingDelayFactor.label>temps de tir</AimingDelayFactor.label>
  <!-- EN: How long it takes to shoot after choosing a target. -->
  <AimingDelayFactor.description>Le temps nécessaire au tir après avoir visé.</AimingDelayFactor.description>
  
  <!-- EN: incoming damage multiplier -->
  <IncomingDamageFactor.label>multiplicateur de dégâts</IncomingDamageFactor.label>
  <!-- EN: A multiplier on all incoming damage. -->
  <IncomingDamageFactor.description>Un multiplicateur sur tous les dégâts subis.</IncomingDamageFactor.description>
  
  <!-- EN: melee armor penetration -->
  <MeleeArmorPenetration.label>pénétration d'armure en mêlée</MeleeArmorPenetration.label>
  <!-- EN: Average armor penetration of all attacks in melee combat.\n\nThis stat includes currently used weapon. -->
  <MeleeArmorPenetration.description>Pénétration moyenne des armures lors des attaques de mêlée.\n\nCette statistique est pour l'arme actuelle.</MeleeArmorPenetration.description>
  
  <!-- EN: melee dodge chance -->
  <MeleeDodgeChance.label>probabilité d'esquiver en mêlée</MeleeDodgeChance.label>
  <!-- EN: Chance to dodge a melee attack that would've otherwise hit.\n\nCharacters will not dodge while aiming or firing a ranged weapon. -->
  <MeleeDodgeChance.description>Probabilité d'esquiver une attaque de mêlée qui aurait dû atteindre sa cible.\n\nLes personnages ne peuvent pas esquiver lorsqu'ils mettent en joue ou sont en train de tirer.</MeleeDodgeChance.description>
  
  <!-- EN: melee DPS -->
  <MeleeDPS.label>DPS au corps-à-corps</MeleeDPS.label>
  <!-- EN: Average damage per second in melee combat.\n\nThis stat ignores target defenses like dodging and armor. -->
  <MeleeDPS.description>Moyenne des Dommages Par Seconde dans les combats de mêlée.\n\nCela ne prend pas en compte les défenses de la cible, comme ses esquives ou son armure.</MeleeDPS.description>
  
  <!-- EN: melee hit chance -->
  <MeleeHitChance.label>chance de toucher en mêlée</MeleeHitChance.label>
  <!-- EN: Chance to hit a target in melee.\n\nThe target can still dodge even if we would've hit. -->
  <MeleeHitChance.description>Les chances d'atteindre une cible en combat de mêlée.\n\nLa cible peut esquiver même lorsqu'on l'atteint.</MeleeHitChance.description>
  
  <!-- EN: trap spring chance -->
  <PawnTrapSpringChance.label>chance de déclencher un piège</PawnTrapSpringChance.label>
  <!-- EN: Chance to spring a trap the character is unaware of. -->
  <PawnTrapSpringChance.description>Chance de déclencher un piège que ce personnage n'a pas vu.</PawnTrapSpringChance.description>
  
  <!-- EN: shooting accuracy -->
  <ShootingAccuracyPawn.label>précision de tir</ShootingAccuracyPawn.label>
  <!-- EN: Base chance to not miss per cell of shot distance.\n\nChance to hit is also affected by many other factors.\n\nA hit chance explanation for any shot can be seen by selecting a shooter and mousing over a target. -->
  <ShootingAccuracyPawn.description>Chance de base de réussir chaque tir.\n\nLa chance de toucher est également affectée par de nombreux autres facteurs.\n\nOn peut avoir une explication pour n'importe quel tir en sélectionnant un tireur et en survolant une cible.</ShootingAccuracyPawn.description>
  <!-- EN: shooting accuracy (people) -->
  <ShootingAccuracyPawn.labelForFullStatList>précision de tir (personnes)</ShootingAccuracyPawn.labelForFullStatList>
  
</LanguageData>