<?xml version="1.0" encoding="utf-8"?>
<LanguageData>

  <Torso.label>torse</Torso.label>
  <UpperHead.label>crâne</UpperHead.label>
  <FullHead.label>tête</FullHead.label>
  <Eyes.label>yeux</Eyes.label>
  <Teeth.label>dents</Teeth.label>
  <Mouth.label>bouche</Mouth.label>
  <Neck.label>cou</Neck.label>
  <Arms.label>bras</Arms.label>
  <Shoulders.label>épaules</Shoulders.label>
  <Hands.label>mains</Hands.label>

  <LeftHand.label>avant-bras gauche</LeftHand.label>
  <LeftHand.labelShort>fist</LeftHand.labelShort>

  <RightHand.label>avant-bras droit</RightHand.label>
  <RightHand.labelShort>fist</RightHand.labelShort>

  <Waist.label>taille</Waist.label>
  <Legs.label>jambes</Legs.label>
  <Feet.label>pieds</Feet.label>

  <FrontLeftPaw.label>patte avant gauche</FrontLeftPaw.label>
  <FrontLeftPaw.labelShort>paw</FrontLeftPaw.labelShort>

  <FrontRightPaw.label>patte avant droite</FrontRightPaw.label>
  <FrontRightPaw.labelShort>paw</FrontRightPaw.labelShort>

  <HeadAttackTool.label>tête</HeadAttackTool.label>

  <FrontLeftLeg.label>patte avant gauche</FrontLeftLeg.label>
  <FrontLeftLeg.labelShort>leg</FrontLeftLeg.labelShort>

  <FrontRightLeg.label>patte avant droite</FrontRightLeg.label>
  <FrontRightLeg.labelShort>leg</FrontRightLeg.labelShort>

  <FrontLeftClaws.label>griffe avant gauche</FrontLeftClaws.label>
  <FrontLeftClaws.labelShort>claws</FrontLeftClaws.labelShort>

  <FrontRightClaws.label>griffe avant droite</FrontRightClaws.label>
  <FrontRightClaws.labelShort>claws</FrontRightClaws.labelShort>

  <LeftBlade.label>lame gauche</LeftBlade.label>
  <LeftBlade.labelShort>blade</LeftBlade.labelShort>

  <RightBlade.label>lame droite</RightBlade.label>
  <RightBlade.labelShort>blade</RightBlade.labelShort>

  <TuskAttackTool.label>défenses</TuskAttackTool.label>
  <HornAttackTool.label>corne</HornAttackTool.label>
  <HeadClaw.label>griffes</HeadClaw.label>
  <TurtleBeakAttackTool.label>bec</TurtleBeakAttackTool.label>
  <Beak.label>bec</Beak.label>


</LanguageData>
