<?xml version="1.0" encoding="UTF-8"?>
<LanguageData>

  <!-- ======================== Non-grouped ========================-->
  
  <!-- EN: Your faction will be a {0}. -->
  <ScenPart_PlayerFaction>Votre faction sera : {0}.</ScenPart_PlayerFaction>

  <!-- EN: Start with {0} people, chosen from {1}. -->
  <ScenPart_StartWithPawns>Commencer avec {0} personnage{0_multiple ? s : }, à choisir parmi {1}.</ScenPart_StartWithPawns>
  <!-- EN: chosen from -->
  <ScenPart_StartWithPawns_OutOf>choisis parmi</ScenPart_StartWithPawns_OutOf>
  <!-- EN: random pet -->
  <RandomPet>animal familier aléatoire</RandomPet>

  <!-- EN: Start with research: {0} -->
  <ScenPart_StartingResearchFinished>Commence avec la recherche : {0}</ScenPart_StartingResearchFinished>
  
  <!-- EN: Arrive in drop pods. -->
  <ScenPart_ArriveInDropPods>Arriver en capsule de largage.</ScenPart_ArriveInDropPods>

  <!-- EN: The stat "{0}" will be universally multiplied by {1}. -->
  <ScenPart_StatFactor>L'attribut "{0}" sera universellement multiplié par {1}.</ScenPart_StatFactor>

  <!-- Pawn modifiers -->
  <!-- EN: {0} have a {1} chance to start with {2}. -->
  <ScenPart_PawnsHaveHediff>{0} a {1} de chances de démarrer avec {2}.</ScenPart_PawnsHaveHediff>
  <!-- EN: severity: {0} -->
  <ConfigurableSeverity>sévérité : {0}</ConfigurableSeverity>

  <!-- EN: {0} have a {1} chance to have their {2} set between {3} and {4}. -->
  <ScenPart_SetNeed>{0} ont {1} de chances d'avoir leur {2} défini entre {3} et {4}.</ScenPart_SetNeed>
  <!-- EN: level: {0} -->
  <ConfigurableLevel>niveau : {0}</ConfigurableLevel>

  <!-- EN: {0} have a {1} chance to start with trait: {2} -->
  <ScenPart_PawnsHaveTrait>{0} ont {1} de chances de commencer avec le trait : {2}</ScenPart_PawnsHaveTrait>
  <!-- EN: Characters and creatures explode on death ({0}, radius {1}). -->
  <ScenPart_OnPawnDeathExplode>Les personnages et créatures explosent à leur mort ({0}, rayon {1}).</ScenPart_OnPawnDeathExplode>
  <!-- EN: {0} start naked. -->
  <ScenPart_PawnsAreNaked>{0} débutent nus.</ScenPart_PawnsAreNaked>
  
  <!-- Pawn filters -->
  <!-- EN: Your people will be at least {0} years old. -->
  <ScenPart_StartingPawnAgeMin>Vos personnages auront au moins {0} ans.</ScenPart_StartingPawnAgeMin>
  <!-- EN: Your people will be at most {0} years old. -->
  <ScenPart_StartingPawnAgeMax>Vos personnages n'auront pas plus de {0} ans.</ScenPart_StartingPawnAgeMax>
  <!-- EN: Your people will be between {0} and {1} years old. -->
  <ScenPart_StartingPawnAgeRange>Vos personnages auront entre {0} et {1} ans.</ScenPart_StartingPawnAgeRange>

  <!-- ======================== Grouped ========================-->

  <!-- EN: Start with -->
  <ScenPart_StartWith>Commencer avec</ScenPart_StartWith>
  <!-- EN: Map is scattered with -->
  <ScenPart_MapScatteredWith>La carte sera parsemée de</ScenPart_MapScatteredWith>
  <!-- EN: Permanent game condition(s) -->
  <ScenPart_PermaGameCondition>Condition(s) de jeu permanente(s)</ScenPart_PermaGameCondition>
  <!-- EN: Incident(s) disabled -->
  <ScenPart_DisableIncident>Incident(s) désactivé(s)</ScenPart_DisableIncident>
  <!-- EN: Incident created -->
  <ScenPart_CreateIncident>Incident(s) programmé(s)</ScenPart_CreateIncident>
  <!-- EN: Can never build -->
  <ScenPart_DisallowBuilding>Impossible de construire</ScenPart_DisallowBuilding>

</LanguageData>